cobaldeval/__init__.py
cobaldeval/evaluate.py
cobaldeval/lca.py
cobaldeval/parsing.py
cobaldeval/scorer.py
cobaldeval/taxonomy.py
cobaldeval/res/feats_weights.json
cobaldeval/res/hyperonims_hierarchy.csv
cobaldeval/res/lemma_weights.json
cobaldeval-1.0.7.dist-info/licenses/LICENSE
cobaldeval-1.0.7.dist-info/METADATA
cobaldeval-1.0.7.dist-info/WHEEL
cobaldeval-1.0.7.dist-info/entry_points.txt
cobaldeval-1.0.7.dist-info/top_level.txt
cobaldeval-1.0.7.dist-info/RECORD
